README.txt
pygenomes.py
setup.py
pygenomes.egg-info/PKG-INFO
pygenomes.egg-info/SOURCES.txt
pygenomes.egg-info/dependency_links.txt
pygenomes.egg-info/entry_points.txt
pygenomes.egg-info/not-zip-safe
pygenomes.egg-info/top_level.txt