Metadata-Version: 1.1
Name: pygenomes
Version: 0.1.0
Summary: a command-line tool for downloading genome data from UCSC ftp site.
Home-page: https://github.com/TinyNecessaryTools/Biology
Author: FEI YUAN
Author-email: fyuan4@uh.edu
License: MIT
Download-URL: https://github.com/TinyNecessaryTools/Biology/pygenomes/dist/pygenomes-0.1.0.tar.gz
Keywords: genome,download,ucsc,bioinformatic,biology
Platform: Posix
Platform: Windows
Classifier: Development Status :: 3 - Alpha
Classifier: Environment :: Console
Classifier: Intended Audience :: End Users/Desktop
Classifier: Operating System :: MacOS :: MacOS X
Classifier: Operating System :: POSIX
Classifier: Operating System :: Microsoft :: Windows
Classifier: Programming Language :: Python
Classifier: Topic :: Utilities
